mlaunch/AutoML.py
mlaunch/__init__.py
mlaunch/api.py
mlaunch/core/__init__.py
mlaunch/core/data_cleaning.py
mlaunch/core/data_info.py
mlaunch/core/data_io.py
mlaunch/core/evaluation.py
mlaunch/core/modeling.py
mlaunch/core/preprocessing.py
mlaunch/core/utils.py
mlaunch-0.2.1.dist-info/licenses/LICENSE
mlaunch-0.2.1.dist-info/METADATA
mlaunch-0.2.1.dist-info/WHEEL
mlaunch-0.2.1.dist-info/top_level.txt
mlaunch-0.2.1.dist-info/RECORD
