Metadata-Version: 2.4
Name: mlaunch
Version: 0.2.1
Summary: Automatic ML pipeline builder
Author-email: Abdulrahman Alowidi <abode.bader@outlook.sa>
License: MIT License
Project-URL: Homepage, https://github.com/Abode-18
Keywords: ML,AutoML,Pipeline
Classifier: Programming Language :: Python :: 3
Classifier: License :: OSI Approved :: MIT License
Classifier: Operating System :: OS Independent
Requires-Python: >=3.7
License-File: LICENSE
Requires-Dist: pandas
Requires-Dist: numpy
Requires-Dist: scikit-learn
Requires-Dist: joblib
Requires-Dist: category_encoders
Dynamic: license-file
